tdlib/__init__.py
tdlib/loaders.py
tdlib/renderer.py
tdlib3d-1.0.0.dist-info/METADATA
tdlib3d-1.0.0.dist-info/WHEEL
tdlib3d-1.0.0.dist-info/top_level.txt
tdlib3d-1.0.0.dist-info/RECORD
