Metadata-Version: 2.4
Name: tdlib3d
Version: 1.0.0
Summary: A lightweight 3D rendering library for Python
Author-email: Anand Kumar <your.email@example.com>
Project-URL: Homepage, https://github.com/yourusername/tdlib3d
Classifier: Programming Language :: Python :: 3
Classifier: License :: OSI Approved :: MIT License
Classifier: Operating System :: OS Independent
Classifier: Topic :: Multimedia :: Graphics :: 3D Rendering
Requires-Python: >=3.8
Requires-Dist: moderngl
Requires-Dist: pygame-ce
Requires-Dist: numpy
Requires-Dist: pyrr
Requires-Dist: trimesh
Requires-Dist: Pillow
